LICENSE
README.md
setup.cfg
setup.py
codev/__init__.py
codev/agent.py
codev/approvals.py
codev/cli.py
codev/commands.py
codev/config.py
codev/format_command.py
codev/history_manager.py
codev/models.py
codev/terminal_chat.py
codev/tools.py
codev/version.py
pycodev.egg-info/PKG-INFO
pycodev.egg-info/SOURCES.txt
pycodev.egg-info/dependency_links.txt
pycodev.egg-info/entry_points.txt
pycodev.egg-info/not-zip-safe
pycodev.egg-info/requires.txt
pycodev.egg-info/top_level.txt
tests/test_issue.py