Metadata-Version: 2.4
Name: pycodev
Version: 0.1.1
Summary: codev: Code Agent for Python
Home-page: https://github.com/shibing624/codev
Author: XuMing
Author-email: xuming624@qq.com
License: Apache License 2.0
Keywords: codev,code-agent,code-completion,code-generation,code-assistant
Classifier: Intended Audience :: Developers
Classifier: Operating System :: OS Independent
Classifier: Natural Language :: Chinese (Simplified)
Classifier: Natural Language :: Chinese (Traditional)
Classifier: Programming Language :: Python
Classifier: Programming Language :: Python :: 3
Classifier: Topic :: Text Processing
Classifier: Topic :: Text Processing :: Indexing
Classifier: Topic :: Text Processing :: Linguistic
Requires-Python: >=3.8.0
License-File: LICENSE
Requires-Dist: loguru
Requires-Dist: openai
Dynamic: author
Dynamic: author-email
Dynamic: classifier
Dynamic: description
Dynamic: description-content-type
Dynamic: home-page
Dynamic: keywords
Dynamic: license
Dynamic: license-file
Dynamic: requires-dist
Dynamic: requires-python
Dynamic: summary
